{
  "city": "Samarkand",
  "year": 2022,
  "metadata": {
    "urban_buffer_m": 12000,
    "rural_buffer_m": 25000,
    "center_coordinates": [
      66.9597,
      39.6542
    ],
    "analysis_months": [
      6,
      7,
      8
    ],
    "collection_dates": "2022-06-01 to 2022-08-31",
    "optimization_note": "Focused on summer months only for efficiency"
  },
  "summer_season_summary": {
    "focus_months": [
      6,
      7,
      8
    ],
    "urban": {
      "day": {
        "mean": 38.02493612603562,
        "std_dev": 2.0256853883992494,
        "min": 33.370000000000005,
        "max": 44.120000000000005,
        "p5": 34.84853417266189,
        "p10": 35.47363636363639,
        "p25": 36.52376146788995,
        "median": 37.924437367303625,
        "p75": 39.52714285714289,
        "p90": 40.77304347826091,
        "p95": 41.408571428571456,
        "count": 633
      },
      "night": {
        "mean": 19.778063220056787,
        "std_dev": 1.1983623804173573,
        "min": 17.400000000000034,
        "max": 22.30000000000001,
        "p5": 17.855454545454567,
        "p10": 18.20059446733377,
        "p25": 18.854980468750018,
        "median": 19.760000000000048,
        "p75": 20.732500000000016,
        "p90": 21.42500000000001,
        "p95": 21.89400000000004,
        "count": 633
      }
    },
    "rural": {
      "day": {
        "mean": 37.442452953368566,
        "std_dev": 3.2948572378546346,
        "min": 30.200000000000045,
        "max": 46.460000000000036,
        "p5": 33.18096390622369,
        "p10": 33.68933362180878,
        "p25": 35.060881712162,
        "median": 36.6801882976498,
        "p75": 39.30335245046926,
        "p90": 42.816775181922644,
        "p95": 43.941912345354076,
        "count": 5145
      },
      "night": {
        "mean": 18.772073553740036,
        "std_dev": 1.296588322995271,
        "min": 12.730000000000018,
        "max": 22.32000000000005,
        "p5": 17.154354269583653,
        "p10": 17.46813965458084,
        "p25": 17.963012004365257,
        "median": 18.595655332752145,
        "p75": 19.461646940598513,
        "p90": 20.718229823978774,
        "p95": 21.214767787333887,
        "count": 5145
      }
    },
    "urban_rural_difference": {
      "day": 0.5824831726670539,
      "night": 1.0059896663167507
    }
  },
  "uncertainty": {
    "urban": {
      "day": {
        "mean": 38.02493612603562,
        "stdDev": 2.0031782487623975,
        "count": 580,
        "stdError": 0.0831774494505239,
        "ci95": [
          37.861908325112594,
          38.187963926958645
        ]
      },
      "night": {
        "mean": 19.778063220056787,
        "stdDev": 1.189277298808036,
        "count": 580,
        "stdError": 0.04938205197933652,
        "ci95": [
          19.681274398177287,
          19.874852041936286
        ]
      }
    },
    "rural": {
      "day": {
        "mean": 37.442452953368566,
        "stdDev": 3.295112764073519,
        "count": 4953,
        "stdError": 0.04682050756798703,
        "ci95": [
          37.35068475853531,
          37.53422114820182
        ]
      },
      "night": {
        "mean": 18.772073553740036,
        "stdDev": 1.289842234480153,
        "count": 4953,
        "stdError": 0.01832746628868932,
        "ci95": [
          18.736151719814206,
          18.807995387665866
        ]
      }
    },
    "spatial_uncertainty": {},
    "temporal_uncertainty": {
      "urban": {
        "day": {},
        "night": {}
      },
      "rural": {
        "day": {},
        "night": {}
      }
    }
  },
  "confidence_intervals": {
    "urban": {
      "day": {
        "mean": 38.02493612603562,
        "standard_error": 0.08051376588679507,
        "margin_of_error": 0.15780698113811834,
        "lower_bound": 37.867129144897504,
        "upper_bound": 38.182743107173735,
        "sample_count": 633
      },
      "night": {
        "mean": 19.778063220056787,
        "standard_error": 0.0476306284761773,
        "margin_of_error": 0.09335603181330751,
        "lower_bound": 19.68470718824348,
        "upper_bound": 19.871419251870094,
        "sample_count": 633
      }
    },
    "rural": {
      "day": {
        "mean": 37.442452953368566,
        "standard_error": 0.04593502026824772,
        "margin_of_error": 0.09003263972576553,
        "lower_bound": 37.3524203136428,
        "upper_bound": 37.53248559309433,
        "sample_count": 5145
      },
      "night": {
        "mean": 18.772073553740036,
        "standard_error": 0.018076294842790018,
        "margin_of_error": 0.03542953789186844,
        "lower_bound": 18.736644015848167,
        "upper_bound": 18.807503091631904,
        "sample_count": 5145
      }
    },
    "urban_rural_difference": {
      "day": {
        "difference_mean": 0.5824831726670539,
        "standard_error": 0.0926956988447575,
        "margin_of_error": 0.1816835697357247,
        "lower_bound": 0.40079960293132916,
        "upper_bound": 0.7641667424027785
      },
      "night": {
        "difference_mean": 1.0059896663167507,
        "standard_error": 0.05094535508050865,
        "margin_of_error": 0.09985289595779696,
        "lower_bound": 0.9061367703589537,
        "upper_bound": 1.1058425622745476
      }
    },
    "confidence_level": 0.95
  },
  "day_night_analysis": {
    "urban": {
      "day_temperature": {
        "mean": 38.02493612603562,
        "std_dev": 2.0256853883992494
      },
      "night_temperature": {
        "mean": 19.778063220056787,
        "std_dev": 1.1983623804173573
      },
      "day_night_difference": {
        "mean": 18.246872905978844,
        "std_dev": 1.184524346445119
      }
    },
    "rural": {
      "day_temperature": {
        "mean": 37.442452953368566,
        "std_dev": 3.2948572378546346
      },
      "night_temperature": {
        "mean": 18.772073553740036,
        "std_dev": 1.296588322995271
      },
      "day_night_difference": {
        "mean": 18.670379399628587,
        "std_dev": 2.676119207849778
      }
    },
    "urban_rural_comparison": {
      "day_difference": 0.5824831726670539,
      "night_difference": 1.0059896663167507
    },
    "day_night_differences": {
      "urban_day_night_range": 18.246872905978844,
      "rural_day_night_range": 18.670379399628587,
      "urban_rural_day_night_difference": -0.423506493649743,
      "interpretation": {
        "urban_has_larger_day_night_range": false,
        "urban_day_night_range_larger_by": null
      }
    }
  }
}