{
  "city": "Nurafshon",
  "city_info": {
    "lat": 41.0167,
    "lon": 69.3417,
    "buffer_m": 8000,
    "type": "city",
    "population": 150000
  },
  "facilities": {
    "schools": [
      {
        "id": "maktablar_ochiq.11422",
        "name": "1-sonli umumiy o'rta ta'lim maktab filiali",
        "name_en": "1-school branch",
        "viloyat": "Toshkent viloyati",
        "tuman": "Oqqo`rg`on tumani",
        "coordinates": [
          69.2582,
          40.990475
        ],
        "capacity": 30,
        "enrolled_students": 20,
        "shifts": 1,
        "construction_year": "1980",
        "renovation_year": "2024",
        "building_material": "gisht",
        "sanitation": {
          "electricity": "elektr_bor",
          "water_source": "ichimlik_suvi_manbaa_lokal",
          "internet": "umuman_yuq",
          "sports_hall": "sport_zal_umuman_yuq",
          "activity_hall": "aktiv_zal_umuman_yuq",
          "dining_hall": "oshhona_umuman_yuq"
        }
      },
      {
        "id": "maktablar_ochiq.12172",
        "name": "32-sonli umumiy o'rta ta'lim maktab filiali",
        "name_en": "32-school branch",
        "viloyat": "Toshkent viloyati",
        "tuman": "Oqqo`rg`on tumani",
        "coordinates": [
          69.2582,
          40.990475
        ],
        "capacity": 60,
        "enrolled_students": 29,
        "shifts": 1,
        "construction_year": "2020",
        "renovation_year": "2020",
        "building_material": "gisht",
        "sanitation": {
          "electricity": "elektr_bor",
          "water_source": "ichimlik_suvi_manbaa_markaz",
          "internet": "internet_optika",
          "sports_hall": "sport_zal_umuman_yuq",
          "activity_hall": "aktiv_zal_umuman_yuq",
          "dining_hall": "oshhona_bor_ishlamaydi"
        }
      },
      {
        "id": "maktablar_ochiq.723",
        "name": "22-sonli umumiy o'rta ta'lim maktabi",
        "name_en": "22-secondary school",
        "viloyat": "Toshkent viloyati",
        "tuman": "O'rtachirchiq tumani",
        "coordinates": [
          69.25852358,
          41.0448434
        ],
        "capacity": 160,
        "enrolled_students": 121,
        "shifts": 2,
        "construction_year": "2008",
        "renovation_year": "2008",
        "building_material": "beton",
        "sanitation": {
          "electricity": "elektr_qisman",
          "water_source": "ichimlik_suvi_yuq",
          "internet": "internet_mobil",
          "sports_hall": "sport_zal_umuman_yuq",
          "activity_hall": "aktiv_zal_umuman_yuq",
          "dining_hall": "oshhona_umuman_yuq"
        }
      },
      {
        "id": "maktablar_ochiq.822",
        "name": "36-sonli umumiy o'rta ta'lim maktabi",
        "name_en": "36-secondary school",
        "viloyat": "Toshkent viloyati",
        "tuman": "O'rtachirchiq tumani",
        "coordinates": [
          69.32688658,
          41.06169406
        ],
        "capacity": 320,
        "enrolled_students": 257,
        "shifts": 1,
        "construction_year": "1977",
        "renovation_year": "2021",
        "building_material": "gisht",
        "sanitation": {
          "electricity": "elektr_bor",
          "water_source": "ichimlik_suvi_yuq",
          "internet": "internet_optika",
          "sports_hall": "sport_zal_qoniqarli",
          "activity_hall": "aktiv_zal_qoniqarli",
          "dining_hall": "oshhona_umuman_yuq"
        }
      },
      {
        "id": "maktablar_ochiq.909",
        "name": "30-sonli umumiy o'rta ta'lim maktabi",
        "name_en": "30-secondary school",
        "viloyat": "Toshkent viloyati",
        "tuman": "Piskent tumani",
        "coordinates": [
          69.28448603,
          40.98522969
        ],
        "capacity": 260,
        "enrolled_students": 184,
        "shifts": 1,
        "construction_year": "1982",
        "renovation_year": "2009",
        "building_material": "gisht",
        "sanitation": {
          "electricity": "elektr_bor",
          "water_source": "ichimlik_suvi_manbaa_markaz",
          "internet": "internet_optika",
          "sports_hall": "sport_zal_qoniqarli",
          "activity_hall": "aktiv_zal_umuman_yuq",
          "dining_hall": "oshhona_umuman_yuq"
        }
      },
      {
        "id": "maktablar_ochiq.973",
        "name": "6-sonli umumiy o'rta ta'lim maktabi",
        "name_en": "6-secondary school",
        "viloyat": "Toshkent viloyati",
        "tuman": "O'rtachirchiq tumani",
        "coordinates": [
          69.41753846,
          41.00121367
        ],
        "capacity": 210,
        "enrolled_students": 265,
        "shifts": 2,
        "construction_year": "2008",
        "renovation_year": "",
        "building_material": "gisht",
        "sanitation": {
          "electricity": "elektr_bor",
          "water_source": "ichimlik_suvi_manbaa_lokal",
          "internet": "internet_optika",
          "sports_hall": "sport_zal_umuman_yuq",
          "activity_hall": "aktiv_zal_umuman_yuq",
          "dining_hall": "oshhona_umuman_yuq"
        }
      },
      {
        "id": "maktablar_ochiq.3007",
        "name": "48-sonli umumiy o'rta ta'lim maktabi",
        "name_en": "48-secondary school",
        "viloyat": "Toshkent viloyati",
        "tuman": "Nurafshon shahar",
        "coordinates": [
          69.35702178,
          41.02495683
        ],
        "capacity": 1260,
        "enrolled_students": 1268,
        "shifts": 2,
        "construction_year": "2021",
        "renovation_year": "",
        "building_material": "gisht",
        "sanitation": {
          "electricity": "elektr_qisman",
          "water_source": "ichimlik_suvi_manbaa_markaz",
          "internet": "internet_optika",
          "sports_hall": "sport_zal_qoniqarli",
          "activity_hall": "aktiv_zal_qoniqarli",
          "dining_hall": "oshhona_holati_qoniqarli"
        }
      },
      {
        "id": "maktablar_ochiq.3145",
        "name": "51-sonli umumiy o'rta ta'lim maktabi",
        "name_en": "51-secondary school",
        "viloyat": "Toshkent viloyati",
        "tuman": "O'rtachirchiq tumani",
        "coordinates": [
          69.30651341,
          40.99876896
        ],
        "capacity": 1104,
        "enrolled_students": 882,
        "shifts": 2,
        "construction_year": "1974",
        "renovation_year": "2010",
        "building_material": "gisht",
        "sanitation": {
          "electricity": "elektr_bor",
          "water_source": "ichimlik_suvi_manbaa_markaz",
          "internet": "internet_optika",
          "sports_hall": "sport_zal_qoniqarli",
          "activity_hall": "aktiv_zal_qoniqarli",
          "dining_hall": "oshhona_holati_qoniqarli"
        }
      },
      {
        "id": "maktablar_ochiq.3152",
        "name": "69-sonli umumiy o'rta ta'lim maktabi",
        "name_en": "69-secondary school",
        "viloyat": "Toshkent viloyati",
        "tuman": "O'rtachirchiq tumani",
        "coordinates": [
          69.30426795,
          41.02880109
        ],
        "capacity": 330,
        "enrolled_students": 318,
        "shifts": 1,
        "construction_year": "1964",
        "renovation_year": "2021",
        "building_material": "gisht",
        "sanitation": {
          "electricity": "elektr_qisman",
          "water_source": "ichimlik_suvi_yuq",
          "internet": "internet_optika",
          "sports_hall": "sport_zal_qoniqarli",
          "activity_hall": "aktiv_zal_umuman_yuq",
          "dining_hall": "oshhona_bor_ishlamaydi"
        }
      },
      {
        "id": "maktablar_ochiq.3480",
        "name": "1-sonli umumiy o'rta ta'lim maktabi",
        "name_en": "1-secondary school",
        "viloyat": "Toshkent viloyati",
        "tuman": "Nurafshon shahar",
        "coordinates": [
          69.3612812,
          41.04946925
        ],
        "capacity": 1290,
        "enrolled_students": 1740,
        "shifts": 2,
        "construction_year": "1989",
        "renovation_year": "2018",
        "building_material": "gisht",
        "sanitation": {
          "electricity": "elektr_bor",
          "water_source": "ichimlik_suvi_manbaa_markaz",
          "internet": "internet_optika",
          "sports_hall": "sport_zal_qoniqarli",
          "activity_hall": "aktiv_zal_qoniqarli",
          "dining_hall": "oshhona_holati_qoniqarli"
        }
      },
      {
        "id": "maktablar_ochiq.3955",
        "name": "11-sonli umumiy o'rta ta'lim maktabi",
        "name_en": "11-secondary school",
        "viloyat": "Toshkent viloyati",
        "tuman": "O'rtachirchiq tumani",
        "coordinates": [
          69.37167102,
          40.97680391
        ],
        "capacity": 540,
        "enrolled_students": 725,
        "shifts": 2,
        "construction_year": "1969",
        "renovation_year": "2006",
        "building_material": "gisht",
        "sanitation": {
          "electricity": "elektr_bor",
          "water_source": "ichimlik_suvi_manbaa_lokal",
          "internet": "internet_optika",
          "sports_hall": "sport_zal_qoniqarli",
          "activity_hall": "aktiv_zal_bor_mebel_yuq",
          "dining_hall": "oshhona_holati_qoniqarli"
        }
      },
      {
        "id": "maktablar_ochiq.3976",
        "name": "16-sonli umumiy o'rta ta'lim maktabi",
        "name_en": "16-secondary school",
        "viloyat": "Toshkent viloyati",
        "tuman": "O'rtachirchiq tumani",
        "coordinates": [
          69.30295599,
          41.07435052
        ],
        "capacity": 620,
        "enrolled_students": 728,
        "shifts": 2,
        "construction_year": "1979",
        "renovation_year": "2015",
        "building_material": "gisht",
        "sanitation": {
          "electricity": "elektr_bor",
          "water_source": "ichimlik_suvi_manbaa_lokal",
          "internet": "internet_optika",
          "sports_hall": "sport_zal_qoniqarli",
          "activity_hall": "aktiv_zal_qoniqarli",
          "dining_hall": "oshhona_holati_qisman_tamir"
        }
      },
      {
        "id": "maktablar_ochiq.3993",
        "name": "18-sonli umumiy o'rta ta'lim maktabi",
        "name_en": "18-secondary school",
        "viloyat": "Toshkent viloyati",
        "tuman": "O'rtachirchiq tumani",
        "coordinates": [
          69.34327997,
          40.98351285
        ],
        "capacity": 200,
        "enrolled_students": 180,
        "shifts": 1,
        "construction_year": "1994",
        "renovation_year": "2019",
        "building_material": "beton",
        "sanitation": {
          "electricity": "elektr_bor",
          "water_source": "ichimlik_suvi_manbaa_markaz",
          "internet": "internet_mobil",
          "sports_hall": "sport_zal_umuman_yuq",
          "activity_hall": "aktiv_zal_umuman_yuq",
          "dining_hall": "oshhona_umuman_yuq"
        }
      },
      {
        "id": "maktablar_ochiq.4017",
        "name": "27-sonli umumiy o'rta ta'lim maktabi",
        "name_en": "27-secondary school",
        "viloyat": "Toshkent viloyati",
        "tuman": "O'rtachirchiq tumani",
        "coordinates": [
          69.40850686,
          41.00692362
        ],
        "capacity": 620,
        "enrolled_students": 554,
        "shifts": 2,
        "construction_year": "1990",
        "renovation_year": "2017",
        "building_material": "gisht",
        "sanitation": {
          "electricity": "elektr_bor",
          "water_source": "ichimlik_suvi_manbaa_lokal",
          "internet": "internet_optika",
          "sports_hall": "sport_zal_qoniqarli",
          "activity_hall": "aktiv_zal_bor_mebel_yuq",
          "dining_hall": "oshhona_holati_qisman_tamir"
        }
      },
      {
        "id": "maktablar_ochiq.4134",
        "name": "72-sonli ixtisoslashtirilgan davlat umumta’lim maktabi",
        "name_en": "72-specialized state secondary school",
        "viloyat": "Toshkent viloyati",
        "tuman": "O'rtachirchiq tumani",
        "coordinates": [
          69.33009485,
          41.07729642
        ],
        "capacity": 1418,
        "enrolled_students": 1418,
        "shifts": 2,
        "construction_year": "2012",
        "renovation_year": "",
        "building_material": "gisht",
        "sanitation": {
          "electricity": "elektr_qisman",
          "water_source": "ichimlik_suvi_manbaa_lokal",
          "internet": "internet_optika",
          "sports_hall": "sport_zal_qoniqarli",
          "activity_hall": "aktiv_zal_qoniqarli",
          "dining_hall": "oshhona_umuman_yuq"
        }
      },
      {
        "id": "maktablar_ochiq.4481",
        "name": "3-sonli ixtisoslashtirilgan davlat umumta’lim maktabi",
        "name_en": "3-specialized state secondary school",
        "viloyat": "Toshkent viloyati",
        "tuman": "O'rtachirchiq tumani",
        "coordinates": [
          69.3235652,
          41.08432651
        ],
        "capacity": 1040,
        "enrolled_students": 1073,
        "shifts": 2,
        "construction_year": "1986",
        "renovation_year": "2007",
        "building_material": "gisht",
        "sanitation": {
          "electricity": "elektr_qisman",
          "water_source": "ichimlik_suvi_yuq",
          "internet": "internet_optika",
          "sports_hall": "sport_zal_qisman_tamir",
          "activity_hall": "aktiv_zal_qoniqarli",
          "dining_hall": "oshhona_holati_qisman_tamir"
        }
      },
      {
        "id": "maktablar_ochiq.4488",
        "name": "30-sonli umumiy o'rta ta'lim maktabi",
        "name_en": "30-secondary school",
        "viloyat": "Toshkent viloyati",
        "tuman": "O'rtachirchiq tumani",
        "coordinates": [
          69.31591069,
          41.03813123
        ],
        "capacity": 320,
        "enrolled_students": 505,
        "shifts": 2,
        "construction_year": "1985",
        "renovation_year": "2019",
        "building_material": "beton",
        "sanitation": {
          "electricity": "elektr_bor",
          "water_source": "ichimlik_suvi_manbaa_lokal",
          "internet": "internet_optika",
          "sports_hall": "sport_zal_qoniqarli",
          "activity_hall": "aktiv_zal_umuman_yuq",
          "dining_hall": "oshhona_holati_qisman_tamir"
        }
      },
      {
        "id": "maktablar_ochiq.4503",
        "name": "34-sonli umumiy o'rta ta'lim maktabi",
        "name_en": "34-secondary school",
        "viloyat": "Toshkent viloyati",
        "tuman": "O'rtachirchiq tumani",
        "coordinates": [
          69.39607809,
          40.98787075
        ],
        "capacity": 420,
        "enrolled_students": 478,
        "shifts": 2,
        "construction_year": "2017",
        "renovation_year": "2021",
        "building_material": "gisht",
        "sanitation": {
          "electricity": "elektr_qisman",
          "water_source": "ichimlik_suvi_yuq",
          "internet": "internet_optika",
          "sports_hall": "sport_zal_qoniqarli",
          "activity_hall": "aktiv_zal_umuman_yuq",
          "dining_hall": "oshhona_holati_qisman_tamir"
        }
      },
      {
        "id": "maktablar_ochiq.4635",
        "name": "5-sonli umumiy o'rta ta'lim maktabi",
        "name_en": "5-secondary school",
        "viloyat": "Toshkent viloyati",
        "tuman": "O'rtachirchiq tumani",
        "coordinates": [
          69.39382526,
          41.0268457
        ],
        "capacity": 624,
        "enrolled_students": 531,
        "shifts": 1,
        "construction_year": "1983",
        "renovation_year": "2009",
        "building_material": "gisht",
        "sanitation": {
          "electricity": "elektr_bor",
          "water_source": "ichimlik_suvi_manbaa_lokal",
          "internet": "internet_optika",
          "sports_hall": "sport_zal_qoniqarli",
          "activity_hall": "aktiv_zal_qoniqarli",
          "dining_hall": "oshhona_holati_qoniqarli"
        }
      },
      {
        "id": "maktablar_ochiq.6411",
        "name": "9-sonli ixtisoslashtirilgan davlat umumta'lim maktabi",
        "name_en": "9-specialized state secondary school",
        "viloyat": "Toshkent viloyati",
        "tuman": "Nurafshon shahar",
        "coordinates": [
          69.35746231,
          41.0123428
        ],
        "capacity": 512,
        "enrolled_students": 727,
        "shifts": 2,
        "construction_year": "1968",
        "renovation_year": "2019",
        "building_material": "gisht",
        "sanitation": {
          "electricity": "elektr_qisman",
          "water_source": "ichimlik_suvi_manbaa_markaz",
          "internet": "internet_optika",
          "sports_hall": "sport_zal_qisman_tamir",
          "activity_hall": "aktiv_zal_qisman_tamir",
          "dining_hall": "oshhona_holati_qisman_tamir"
        }
      },
      {
        "id": "maktablar_ochiq.6703",
        "name": "32-sonli umumiy o'rta ta'lim maktabi",
        "name_en": "32-secondary school",
        "viloyat": "Toshkent viloyati",
        "tuman": "Nurafshon shahar",
        "coordinates": [
          69.3454553,
          41.06363893
        ],
        "capacity": 480,
        "enrolled_students": 754,
        "shifts": 2,
        "construction_year": "1972",
        "renovation_year": "2024",
        "building_material": "gisht",
        "sanitation": {
          "electricity": "elektr_qisman",
          "water_source": "ichimlik_suvi_manbaa_lokal",
          "internet": "internet_optika",
          "sports_hall": "sport_zal_qisman_tamir",
          "activity_hall": "aktiv_zal_qoniqarli",
          "dining_hall": "oshhona_holati_qoniqarli"
        }
      },
      {
        "id": "maktablar_ochiq.8004",
        "name": "73-sonli umumiy o'rta ta'lim maktabi",
        "name_en": "73-secondary school",
        "viloyat": "Toshkent viloyati",
        "tuman": "Nurafshon shahar",
        "coordinates": [
          69.32446055,
          41.0213023
        ],
        "capacity": 180,
        "enrolled_students": 176,
        "shifts": 1,
        "construction_year": "1994",
        "renovation_year": "2022",
        "building_material": "gisht",
        "sanitation": {
          "electricity": "elektr_bor",
          "water_source": "ichimlik_suvi_manbaa_markaz",
          "internet": "internet_optika",
          "sports_hall": "sport_zal_qoniqarli",
          "activity_hall": "aktiv_zal_umuman_yuq",
          "dining_hall": "oshhona_umuman_yuq"
        }
      },
      {
        "id": "maktablar_ochiq.747",
        "name": "28-sonli umumiy o'rta ta'lim maktabi",
        "name_en": "28-secondary school",
        "viloyat": "Toshkent viloyati",
        "tuman": "O'rtachirchiq tumani",
        "coordinates": [
          69.25895341,
          41.03857597
        ],
        "capacity": 320,
        "enrolled_students": 218,
        "shifts": 1,
        "construction_year": "1966",
        "renovation_year": "2007",
        "building_material": "gisht",
        "sanitation": {
          "electricity": "elektr_bor",
          "water_source": "ichimlik_suvi_manbaa_markaz",
          "internet": "internet_optika",
          "sports_hall": "sport_zal_qoniqarli",
          "activity_hall": "aktiv_zal_qoniqarli",
          "dining_hall": "oshhona_umuman_yuq"
        }
      },
      {
        "id": "maktablar_ochiq.895",
        "name": "43-sonli umumiy o'rta ta'lim maktabi",
        "name_en": "43-secondary school",
        "viloyat": "Toshkent viloyati",
        "tuman": "O'rtachirchiq tumani",
        "coordinates": [
          69.29849116,
          40.99810723
        ],
        "capacity": 440,
        "enrolled_students": 485,
        "shifts": 1,
        "construction_year": "1984",
        "renovation_year": "2022",
        "building_material": "gisht",
        "sanitation": {
          "electricity": "elektr_qisman",
          "water_source": "ichimlik_suvi_manbaa_markaz",
          "internet": "internet_optika",
          "sports_hall": "sport_zal_qoniqarli",
          "activity_hall": "aktiv_zal_qoniqarli",
          "dining_hall": "oshhona_holati_qoniqarli"
        }
      },
      {
        "id": "maktablar_ochiq.1542",
        "name": "26-sonli umumiy o'rta ta'lim maktabi",
        "name_en": "26-secondary school",
        "viloyat": "Toshkent viloyati",
        "tuman": "Nurafshon shahar",
        "coordinates": [
          69.35166253,
          41.04425872
        ],
        "capacity": 740,
        "enrolled_students": 761,
        "shifts": 2,
        "construction_year": "1978",
        "renovation_year": "2015",
        "building_material": "gisht",
        "sanitation": {
          "electricity": "elektr_qisman",
          "water_source": "ichimlik_suvi_manbaa_lokal",
          "internet": "internet_optika",
          "sports_hall": "sport_zal_qisman_tamir",
          "activity_hall": "aktiv_zal_qoniqarli",
          "dining_hall": "oshhona_holati_qoniqarli"
        }
      },
      {
        "id": "maktablar_ochiq.2269",
        "name": "4-sonli umumiy o'rta ta'lim maktabi",
        "name_en": "4-secondary school",
        "viloyat": "Toshkent viloyati",
        "tuman": "Nurafshon shahar",
        "coordinates": [
          69.36137358,
          41.04456343
        ],
        "capacity": 850,
        "enrolled_students": 1087,
        "shifts": 2,
        "construction_year": "1964",
        "renovation_year": "2018",
        "building_material": "gisht",
        "sanitation": {
          "electricity": "elektr_bor",
          "water_source": "ichimlik_suvi_manbaa_markaz",
          "internet": "internet_optika",
          "sports_hall": "sport_zal_qoniqarli",
          "activity_hall": "aktiv_zal_qoniqarli",
          "dining_hall": "oshhona_holati_qoniqarli"
        }
      },
      {
        "id": "maktablar_ochiq.2952",
        "name": "13-sonli umumiy o'rta ta'lim maktabi",
        "name_en": "13-secondary school",
        "viloyat": "Toshkent viloyati",
        "tuman": "Nurafshon shahar",
        "coordinates": [
          69.34183004,
          41.03851479
        ],
        "capacity": 530,
        "enrolled_students": 574,
        "shifts": 2,
        "construction_year": "1971",
        "renovation_year": "2022",
        "building_material": "gisht",
        "sanitation": {
          "electricity": "elektr_qisman",
          "water_source": "ichimlik_suvi_manbaa_markaz",
          "internet": "internet_optika",
          "sports_hall": "sport_zal_qisman_tamir",
          "activity_hall": "aktiv_zal_qisman_tamir",
          "dining_hall": "oshhona_holati_qoniqarli"
        }
      },
      {
        "id": "maktablar_ochiq.2971",
        "name": "15-sonli umumiy o'rta ta'lim maktabi",
        "name_en": "15-secondary school",
        "viloyat": "Toshkent viloyati",
        "tuman": "O'rtachirchiq tumani",
        "coordinates": [
          69.26592663,
          41.01945785
        ],
        "capacity": 560,
        "enrolled_students": 643,
        "shifts": 2,
        "construction_year": "1967",
        "renovation_year": "2007",
        "building_material": "gisht",
        "sanitation": {
          "electricity": "elektr_bor",
          "water_source": "ichimlik_suvi_yuq",
          "internet": "internet_optika",
          "sports_hall": "sport_zal_qoniqarli",
          "activity_hall": "aktiv_zal_qoniqarli",
          "dining_hall": "oshhona_umuman_yuq"
        }
      },
      {
        "id": "maktablar_ochiq.8817",
        "name": "19-sonli umumiy o'rta ta'lim maktabi",
        "name_en": "19-secondary school",
        "viloyat": "Toshkent viloyati",
        "tuman": "Nurafshon shahar",
        "coordinates": [
          69.34961765,
          41.00512459
        ],
        "capacity": 200,
        "enrolled_students": 135,
        "shifts": 2,
        "construction_year": "1960",
        "renovation_year": "",
        "building_material": "gisht",
        "sanitation": {
          "electricity": "elektr_bor",
          "water_source": "ichimlik_suvi_yuq",
          "internet": "internet_optika",
          "sports_hall": "sport_zal_qoniqarli",
          "activity_hall": "aktiv_zal_umuman_yuq",
          "dining_hall": "oshhona_bor_ishlamaydi"
        }
      },
      {
        "id": "maktablar_ochiq.8942",
        "name": "62-sonli umumiy o'rta ta'lim maktabi",
        "name_en": "62-secondary school",
        "viloyat": "Toshkent viloyati",
        "tuman": "Nurafshon shahar",
        "coordinates": [
          69.36963402,
          41.02170656
        ],
        "capacity": 320,
        "enrolled_students": 247,
        "shifts": 2,
        "construction_year": "1987",
        "renovation_year": "2007",
        "building_material": "gisht",
        "sanitation": {
          "electricity": "elektr_qisman",
          "water_source": "ichimlik_suvi_manbaa_markaz",
          "internet": "internet_optika",
          "sports_hall": "sport_zal_umuman_yuq",
          "activity_hall": "aktiv_zal_bor_mebel_yuq",
          "dining_hall": "oshhona_umuman_yuq"
        }
      },
      {
        "id": "maktablar_ochiq.10022",
        "name": "57-sonli umumiy o'rta ta'lim maktabi",
        "name_en": "57-secondary school",
        "viloyat": "Toshkent viloyati",
        "tuman": "Nurafshon shahar",
        "coordinates": [
          69.36173858,
          40.99305926
        ],
        "capacity": 780,
        "enrolled_students": 1262,
        "shifts": 2,
        "construction_year": "1967",
        "renovation_year": "2019",
        "building_material": "gisht",
        "sanitation": {
          "electricity": "elektr_qisman",
          "water_source": "ichimlik_suvi_manbaa_markaz",
          "internet": "internet_optika",
          "sports_hall": "sport_zal_qoniqarli",
          "activity_hall": "aktiv_zal_qoniqarli",
          "dining_hall": "oshhona_holati_qoniqarli"
        }
      },
      {
        "id": "maktablar_ochiq.10024",
        "name": "10-sonli umumiy o'rta ta'lim maktabi",
        "name_en": "10-secondary school",
        "viloyat": "Toshkent viloyati",
        "tuman": "Nurafshon shahar",
        "coordinates": [
          69.37151975,
          40.99037712
        ],
        "capacity": 444,
        "enrolled_students": 565,
        "shifts": 2,
        "construction_year": "1991",
        "renovation_year": "2024",
        "building_material": "gisht",
        "sanitation": {
          "electricity": "elektr_bor",
          "water_source": "ichimlik_suvi_manbaa_markaz",
          "internet": "internet_optika",
          "sports_hall": "sport_zal_qisman_tamir",
          "activity_hall": "aktiv_zal_bor_mebel_yuq",
          "dining_hall": "oshhona_holati_qisman_tamir"
        }
      },
      {
        "id": "maktablar_ochiq.10776",
        "name": "25-sonli umumiy o'rta ta'lim maktabi",
        "name_en": "25-secondary school",
        "viloyat": "Toshkent viloyati",
        "tuman": "Nurafshon shahar",
        "coordinates": [
          69.37613742,
          41.04760708
        ],
        "capacity": 300,
        "enrolled_students": 339,
        "shifts": 2,
        "construction_year": "1976",
        "renovation_year": "2016",
        "building_material": "gisht",
        "sanitation": {
          "electricity": "elektr_qisman",
          "water_source": "ichimlik_suvi_manbaa_markaz",
          "internet": "internet_optika",
          "sports_hall": "sport_zal_qoniqarli",
          "activity_hall": "aktiv_zal_qoniqarli",
          "dining_hall": "oshhona_holati_qoniqarli"
        }
      }
    ],
    "hospitals": [
      {
        "id": "a52bc9a8-4357-4bc0-898f-f7114563f727",
        "name": "Tashkent regional (territorial) branch of the Republican Specialized Cardiology Center for Scientific and Practical Medicine",
        "coordinates": [
          69.30997,
          40.996002
        ],
        "type": "hospital"
      },
      {
        "id": "c8bd3cbb-0efd-46f2-be93-68086bbd3525",
        "name": "Nurafshan SHTB",
        "coordinates": [
          69.35761,
          41.04271
        ],
        "type": "hospital"
      },
      {
        "id": "5e26878f-cf43-4822-98f7-299112e13430",
        "name": "Sanatorium of Tashkent region - center of epidemiological relaxation and public health",
        "coordinates": [
          69.357735,
          41.04025
        ],
        "type": "hospital"
      },
      {
        "id": "89e08aca-3815-4018-a681-dd37e4ec8fd3",
        "name": "Disinfection station in Nurafshon municipal farm",
        "coordinates": [
          69.357735,
          41.04025
        ],
        "type": "hospital"
      },
      {
        "id": "a6c3948c-a9f6-40d3-8894-2beb399a5d8d",
        "name": "Nurafshan City Center for Sanitary-Epidemiological Peace and Public Health",
        "coordinates": [
          69.357735,
          41.04025
        ],
        "type": "hospital"
      },
      {
        "id": "8354e3b4-88de-4c42-afc7-d1f63a8d4f97",
        "name": "Tashkent regional branch of the Republican Emergency Medical Center",
        "coordinates": [
          69.35761,
          41.04271
        ],
        "type": "hospital"
      }
    ],
    "kindergardens_gov": [
      {
        "id": "90da1444-f303-4d37-a927-64cada4923a6",
        "name": "30-dmtt",
        "coordinates": [
          69.29976,
          40.998882
        ],
        "type": "kindergarden-legal"
      },
      {
        "id": "ea2bf6cd-d5f9-4a01-b829-3524e61b9183",
        "name": "31-dmtt",
        "coordinates": [
          69.31034,
          40.997322
        ],
        "type": "kindergarden-legal"
      },
      {
        "id": "875d186b-a29f-4345-b63d-4998b8510cda",
        "name": "5-sonli-davlat-maktabgacha-ta-lim-tashkiloti",
        "coordinates": [
          69.34797,
          41.046608
        ],
        "type": "kindergarden-legal"
      },
      {
        "id": "4ee5af90-42c7-404f-95b5-e117b3741242",
        "name": "36-dmtt",
        "coordinates": [
          69.330574,
          41.07395
        ],
        "type": "kindergarden-legal"
      },
      {
        "id": "f9de7b6d-e1b3-4aeb-8b3c-d8f855e95ff8",
        "name": "26-sonli-davlat-maktabgacha-ta-lim-tashkiloti",
        "coordinates": [
          69.35348,
          41.040916
        ],
        "type": "kindergarden-legal"
      },
      {
        "id": "35d8ee3c-d399-4eb5-b078-94578b0155fb",
        "name": "37-dmtt",
        "coordinates": [
          69.31019,
          41.071976
        ],
        "type": "kindergarden-legal"
      },
      {
        "id": "d7cdb8d6-c7a2-4cf9-87a4-44426431c2f0",
        "name": "7",
        "coordinates": [
          69.31513,
          41.035076
        ],
        "type": "kindergarden-legal"
      },
      {
        "id": "c28fd337-f569-414b-b218-8f5be14944d1",
        "name": "1-dmtt",
        "coordinates": [
          69.31482,
          41.038612
        ],
        "type": "kindergarden-legal"
      },
      {
        "id": "ce6306d7-f510-4a50-8a0d-6f728418986f",
        "name": "3-dmtt",
        "coordinates": [
          69.33183,
          41.07498
        ],
        "type": "kindergarden-legal"
      },
      {
        "id": "4fee5722-a2f4-4a04-b6fc-64c7c0217b41",
        "name": "33-dmtt",
        "coordinates": [
          69.32503,
          41.084522
        ],
        "type": "kindergarden-legal"
      },
      {
        "id": "e3a5d7f3-894d-4a8b-923b-4c785e69bf75",
        "name": "11-sonli-davlat-maktabgacha-ta-lim-tashkiloti",
        "coordinates": [
          69.36132,
          41.008904
        ],
        "type": "kindergarden-legal"
      },
      {
        "id": "bb56b41b-bd62-4b77-9433-fc02b4305ccc",
        "name": "14-sonli-davlat-maktabgacha-ta-lim-tashkiloti",
        "coordinates": [
          69.3605,
          41.028282
        ],
        "type": "kindergarden-legal"
      }
    ],
    "kindergardens_private": [
      {
        "id": "139770c2-b490-4aa2-b236-9304e8390596",
        "name": "Yatt Musaqulova Zulfiya Djo`raboyevna",
        "coordinates": [
          69.34159,
          41.041794
        ],
        "type": "kindergarden"
      },
      {
        "id": "56fc80b8-4b94-4adb-9532-6d9642881b0f",
        "name": "YaTT Xalmuratova Oqila Mirusmonovna",
        "coordinates": [
          69.35474,
          41.056244
        ],
        "type": "kindergarden"
      },
      {
        "id": "e17c3a0f-1c51-4e5a-a95a-dfb5f9540e0f",
        "name": "YaTT Ermatov Zokir Xaitmatovich",
        "coordinates": [
          69.37473,
          41.047657
        ],
        "type": "kindergarden"
      },
      {
        "id": "df5fdafe-a855-4b09-9935-3c650defb4ac",
        "name": "Yatt Xidirova Barno Ilxomovna",
        "coordinates": [
          69.33342,
          41.08045
        ],
        "type": "kindergarden"
      },
      {
        "id": "f6629fd9-0d7d-45ad-8667-8d98f0b40f71",
        "name": "Yatt Xasanshina Albina Maratovna",
        "coordinates": [
          69.26774,
          41.028114
        ],
        "type": "kindergarden"
      },
      {
        "id": "e12962a0-133f-4519-b6e5-08056970b773",
        "name": "Yatt Akromjonov A`zamjon Adxam o`g`li",
        "coordinates": [
          69.34953,
          41.040787
        ],
        "type": "kindergarden"
      },
      {
        "id": "4e1e3b1b-909f-474f-80e4-517fd3e8ade5",
        "name": "Yatt Mirboboyeva Ziyada Kamilevna",
        "coordinates": [
          69.3635,
          41.029255
        ],
        "type": "kindergarden"
      },
      {
        "id": "c1633640-2ec2-4a54-bd9c-6fbc2f78f9d3",
        "name": "Yatt Tursunboyeva Gullola To`xtanazarovna",
        "coordinates": [
          69.35504,
          41.031372
        ],
        "type": "kindergarden"
      },
      {
        "id": "9b26945e-0af1-476b-92b9-816431f1ea4a",
        "name": "Yatt Ergasheva Gulnara Sitdikxojaevna",
        "coordinates": [
          69.31442,
          41.073326
        ],
        "type": "kindergarden"
      },
      {
        "id": "a6dba37b-33bd-4879-8498-88dc0a505137",
        "name": "Yatt Ag`abekova Janar Abduxaliq qizi",
        "coordinates": [
          69.26521,
          41.041683
        ],
        "type": "kindergarden"
      },
      {
        "id": "8fd827ed-79b5-4c03-816f-4a4c9b382075",
        "name": "Yatt Yuldasheva Nazokat Laziz qizi",
        "coordinates": [
          69.3709,
          40.97567
        ],
        "type": "kindergarden"
      },
      {
        "id": "f1aca084-be7f-455c-94cd-62aff9c07d15",
        "name": "Yatt Gadaeva Xilola To`laganovna",
        "coordinates": [
          69.360016,
          40.9709
        ],
        "type": "kindergarden"
      },
      {
        "id": "a66a37d5-8273-4190-9630-7c6190cdbc66",
        "name": "Yatt Akbarov Azamat Qaxramon o`g`li",
        "coordinates": [
          69.34665,
          41.065365
        ],
        "type": "kindergarden"
      },
      {
        "id": "de93ab4b-3199-4d82-861a-a4962ca77bab",
        "name": "Yatt Axmedxodjayeva Lilya Usmanovna",
        "coordinates": [
          69.36405,
          40.997597
        ],
        "type": "kindergarden"
      },
      {
        "id": "511e5366-9a11-46f0-bf33-c311b18551c2",
        "name": "Yatt Muxsumova Sanobar Ilashevna",
        "coordinates": [
          69.349106,
          41.041004
        ],
        "type": "kindergarden"
      },
      {
        "id": "a201a484-962d-47f6-adf3-dc844c866959",
        "name": "Yatt Irmatova Anora Satinboevna",
        "coordinates": [
          69.34987,
          41.040882
        ],
        "type": "kindergarden"
      },
      {
        "id": "7bb4e717-53d8-47bb-adfb-c02ae4a13c69",
        "name": "Yatt Marajapov Jahongir Kamiljonovich",
        "coordinates": [
          69.35029,
          41.061924
        ],
        "type": "kindergarden"
      },
      {
        "id": "ac8634ae-0152-47cb-b3ca-68f9440d1979",
        "name": "Yatt Abduxakimova Tamara XXX",
        "coordinates": [
          69.264046,
          41.016403
        ],
        "type": "kindergarden"
      },
      {
        "id": "63406ae9-4f22-4c06-8890-44affb83dbb5",
        "name": "Yatt Begimqulova Lobarxon Abdisaidovna",
        "coordinates": [
          69.32506,
          41.08741
        ],
        "type": "kindergarden"
      },
      {
        "id": "e06afc96-8e70-4014-85e6-b50e7477633d",
        "name": "YATT Ibragimova Napisa Djalolovna",
        "coordinates": [
          69.35105,
          41.04018
        ],
        "type": "kindergarden"
      },
      {
        "id": "7d98fe86-6cce-44e9-b574-ba462c5dcd1f",
        "name": "Yatt Azizova Maxbuba Anarbaevna",
        "coordinates": [
          69.30051,
          40.995655
        ],
        "type": "kindergarden"
      },
      {
        "id": "d5d87a84-b50a-4194-855b-f55debc8f66d",
        "name": "Yatt Qurbonboyeva Shoira Kazaxbayevna",
        "coordinates": [
          69.32706,
          41.077717
        ],
        "type": "kindergarden"
      },
      {
        "id": "a738dccb-6320-43be-86dd-3c11e2c5136d",
        "name": "Yatt Axatova Feruza Nasrullo qizi",
        "coordinates": [
          69.3021,
          40.999954
        ],
        "type": "kindergarden"
      },
      {
        "id": "d689922d-2be6-4a65-ac13-df6d99c3a5f1",
        "name": "Yatt Barkasheva Kimmatoy Nasrdinovna",
        "coordinates": [
          69.32749,
          41.08556
        ],
        "type": "kindergarden"
      },
      {
        "id": "62881200-e5ab-4fab-84ed-0bcee5a9e7d9",
        "name": "Yatt Yuldasheva Nilufar Laziz qizi",
        "coordinates": [
          69.37092,
          40.97571
        ],
        "type": "kindergarden"
      },
      {
        "id": "476c0ae4-11ce-478f-868d-c3d3f2f7a21b",
        "name": "Yatt Tursunboeva Baxtigul Qosim qizi",
        "coordinates": [
          69.39969,
          41.008972
        ],
        "type": "kindergarden"
      },
      {
        "id": "e11ccc01-e7df-4f74-88fa-392cc777b6c2",
        "name": "Yatt Shomuratov Shohnazar Karimjonovich",
        "coordinates": [
          69.35002,
          41.061825
        ],
        "type": "kindergarden"
      },
      {
        "id": "17f5d7e3-5222-4c9a-bc75-1f6b6bc1215e",
        "name": "Yatt Inayatova Shaxodat Abdumavlayanovna",
        "coordinates": [
          69.282,
          40.998886
        ],
        "type": "kindergarden"
      },
      {
        "id": "873dfc58-59a1-4055-9136-0a064447971e",
        "name": "Yatt Urmanov Kamoliddin Sharofitdinovich",
        "coordinates": [
          69.355484,
          41.055004
        ],
        "type": "kindergarden"
      },
      {
        "id": "a235ebe7-b32b-48e6-85de-656c9adb6f6e",
        "name": "Yatt Irmatova Saida Alijonovna",
        "coordinates": [
          69.36468,
          41.015594
        ],
        "type": "kindergarden"
      },
      {
        "id": "8d284e29-c627-49c0-af7f-230ea4aa3788",
        "name": "YATT Narova Surayyo Abdimavlanovna",
        "coordinates": [
          69.35813,
          41.0531
        ],
        "type": "kindergarden"
      },
      {
        "id": "54b909d3-ba29-4440-ae31-e67cbe9bb17c",
        "name": "Yatt Galimova Saadat Sanovorovna",
        "coordinates": [
          69.3601,
          41.081913
        ],
        "type": "kindergarden"
      },
      {
        "id": "bd585593-edc2-46ad-8633-df7c644422d7",
        "name": "Yatt Umatova Maftuna Temirpo`lat qizi",
        "coordinates": [
          69.32913,
          41.081963
        ],
        "type": "kindergarden"
      },
      {
        "id": "e693005d-d43c-4f2b-b998-8652f2fc790e",
        "name": "Yatt Akkulova Raxima Dexkanovna",
        "coordinates": [
          69.40261,
          41.02629
        ],
        "type": "kindergarden"
      },
      {
        "id": "610a35eb-1981-4f1d-b278-96f682525d52",
        "name": "Yatt Djamalova Sharafat Nugmanovna",
        "coordinates": [
          69.30763,
          41.074974
        ],
        "type": "kindergarden"
      },
      {
        "id": "6ad871b9-935e-4d70-b65f-ff28cff05a87",
        "name": "Yatt Begmatova Moxira Zulfixarovna",
        "coordinates": [
          69.34865,
          41.059113
        ],
        "type": "kindergarden"
      },
      {
        "id": "efe5f0e3-ba1a-481b-829b-237e0fc550b8",
        "name": "Yatt Xudaykulova Muqaddas Mamadaliyevna",
        "coordinates": [
          69.322655,
          41.01805
        ],
        "type": "kindergarden"
      },
      {
        "id": "3dbf19dd-457c-440f-aea9-85b62e6b3c0f",
        "name": "Yatt Yuldasheva Gulnoza Nizamovna",
        "coordinates": [
          69.30719,
          41.027744
        ],
        "type": "kindergarden"
      },
      {
        "id": "54df9ebf-460d-4631-b506-ee4460e9427d",
        "name": "Yatt Kulbekov Sherzod Muxtaralievich",
        "coordinates": [
          69.414215,
          40.976723
        ],
        "type": "kindergarden"
      },
      {
        "id": "5b5da0a4-fbff-42b4-bb3f-7eb583b12cf5",
        "name": "Yatt Ro`ziboyeva Mahmuda Yo`ldoshboyevna",
        "coordinates": [
          69.349686,
          41.040348
        ],
        "type": "kindergarden"
      },
      {
        "id": "9d80828b-b8d1-4303-9449-638165f4032f",
        "name": "Yatt Xalmuratova Muqaddam Rustamovna",
        "coordinates": [
          69.328545,
          41.05506
        ],
        "type": "kindergarden"
      },
      {
        "id": "0eaa6cfc-5c90-4af6-81c4-c5765cad7bf8",
        "name": "Yatt Mamatqulova Sevara Dilmurodovna",
        "coordinates": [
          69.35453,
          41.058315
        ],
        "type": "kindergarden"
      },
      {
        "id": "64aabd64-49f0-4509-85a3-e5b5d8d8a227",
        "name": "Yatt Kulboyeva Gulchehra Turdiboyevna",
        "coordinates": [
          69.36413,
          41.038025
        ],
        "type": "kindergarden"
      },
      {
        "id": "3806a5e7-9219-4599-aed0-826257c1d0e7",
        "name": "Yatt Sherimova Zulfiya Soliyevna",
        "coordinates": [
          69.34915,
          41.05452
        ],
        "type": "kindergarden"
      },
      {
        "id": "c66ec074-dbb4-4bb8-b41c-2c8052ad185f",
        "name": "YaTT Axmedova O`g`iloy Avaz qizi",
        "coordinates": [
          69.372795,
          41.045704
        ],
        "type": "kindergarden"
      },
      {
        "id": "3e8f6811-2446-4376-be04-852cb70beb46",
        "name": "YaTT Furqatova Baxtiniso Furqat qizi",
        "coordinates": [
          69.30479,
          41.050144
        ],
        "type": "kindergarden"
      },
      {
        "id": "6db9eb9c-94d3-430c-916e-e66a2c2d12cb",
        "name": "Yatt Aktaeva Tattigul Djoldasovna",
        "coordinates": [
          69.32483,
          41.060173
        ],
        "type": "kindergarden"
      },
      {
        "id": "b84d524a-4f28-4b2a-a3e7-871f28396cd1",
        "name": "Yatt Karabayeva Gulnoraxon Toxirovna",
        "coordinates": [
          69.350555,
          41.041176
        ],
        "type": "kindergarden"
      },
      {
        "id": "3a432c23-2a0b-4b3a-955c-903e1fd03f96",
        "name": "Yatt Akbarova Nilufar Qaxramon qizi",
        "coordinates": [
          69.34688,
          41.065475
        ],
        "type": "kindergarden"
      },
      {
        "id": "f931d093-55ec-4285-a1ef-b05734460552",
        "name": "Yatt Maxkambaeva Dilnoza Temirbaevna",
        "coordinates": [
          69.421585,
          41.003918
        ],
        "type": "kindergarden"
      },
      {
        "id": "e58f37c4-d67c-440e-9674-1029aa11b600",
        "name": "Yatt Isayeva Nasiba Toshkenboyevna",
        "coordinates": [
          69.34973,
          41.04058
        ],
        "type": "kindergarden"
      },
      {
        "id": "32212840-88f9-4f27-8982-440ff13c9ce2",
        "name": "Yatt Xadjamova Nilufar Sidikdjonovna",
        "coordinates": [
          69.36427,
          41.003704
        ],
        "type": "kindergarden"
      },
      {
        "id": "a21ad32a-b6db-4421-95df-0511a270f7f1",
        "name": "Yatt Yunusov Olimjon Xamidovich",
        "coordinates": [
          69.36308,
          41.033955
        ],
        "type": "kindergarden"
      },
      {
        "id": "7d87fd87-11ec-42e7-b87f-a0fcdfd2fe8d",
        "name": "Yatt Musayeva Dilorom Xudoyberdiyevna",
        "coordinates": [
          69.35834,
          41.00083
        ],
        "type": "kindergarden"
      },
      {
        "id": "509bd678-f703-4d44-ba96-af780fa53e06",
        "name": "Erudit kids planet NTM",
        "coordinates": [
          69.366455,
          41.00343
        ],
        "type": "kindergarden"
      },
      {
        "id": "c40f46ba-18e0-465a-b65f-4dd11b39eb0d",
        "name": "Malyush kids",
        "coordinates": [
          69.364914,
          41.048447
        ],
        "type": "kindergarden"
      },
      {
        "id": "262c44f6-db7f-46d6-bf16-a0ca62836b3c",
        "name": "yatt-nasreddinova-zulhumor-sabirovna",
        "coordinates": [
          69.36006,
          41.040054
        ],
        "type": "kindergarden"
      }
    ]
  },
  "summary": {
    "total_schools": 33,
    "total_hospitals": 6,
    "total_kindergardens": 69,
    "total_students_capacity": 17482,
    "total_students_enrolled": 19249,
    "sanitation_indicators": {
      "electricity_access": 57.6,
      "water_access": 78.8,
      "internet_access": 100.0,
      "sports_facilities": 63.6,
      "dining_facilities": 36.4,
      "activity_halls": 48.5,
      "water_sources": {
        "centralized": 48.5,
        "local": 30.3,
        "carried": 0.0,
        "none": 21.2
      },
      "water_vulnerability_index": 0.388
    },
    "infrastructure_quality": {
      "modern_buildings": 18.2,
      "recently_renovated": 63.6,
      "brick_construction": 90.9,
      "multiple_shifts": 69.7,
      "building_age_vulnerability": 0.212
    },
    "water_by_district": {
      "Toshkent viloyati - Oqqo`rg`on tumani": {
        "total_schools": 2,
        "water_sources_percent": {
          "centralized": 50.0,
          "local": 50.0,
          "carried": 0.0,
          "none": 0.0
        },
        "average_sanitation_score": 0.75
      },
      "Toshkent viloyati - O'rtachirchiq tumani": {
        "total_schools": 17,
        "water_sources_percent": {
          "centralized": 23.5,
          "local": 41.2,
          "carried": 0.0,
          "none": 35.3
        },
        "average_sanitation_score": 0.76
      },
      "Toshkent viloyati - Piskent tumani": {
        "total_schools": 1,
        "water_sources_percent": {
          "centralized": 100.0,
          "local": 0.0,
          "carried": 0.0,
          "none": 0.0
        },
        "average_sanitation_score": 1.0
      },
      "Toshkent viloyati - Nurafshon shahar": {
        "total_schools": 13,
        "water_sources_percent": {
          "centralized": 76.9,
          "local": 15.4,
          "carried": 0.0,
          "none": 7.7
        },
        "average_sanitation_score": 0.71
      }
    },
    "per_capita_metrics": {
      "schools_per_1000": 0.59,
      "hospitals_per_1000": 0.11,
      "kindergardens_per_1000": 1.23,
      "student_capacity_per_1000": 311.07,
      "enrolled_students_per_1000": 342.51,
      "water_vulnerability_index": 0.388,
      "population": 56200
    }
  }
}